karton_yaramatcher-1.3.0-nspkg.pth
karton/yaramatcher/__init__.py
karton/yaramatcher/__main__.py
karton/yaramatcher/__version__.py
karton/yaramatcher/yaramatcher.py
karton_yaramatcher-1.3.0.dist-info/LICENSE
karton_yaramatcher-1.3.0.dist-info/METADATA
karton_yaramatcher-1.3.0.dist-info/WHEEL
karton_yaramatcher-1.3.0.dist-info/entry_points.txt
karton_yaramatcher-1.3.0.dist-info/namespace_packages.txt
karton_yaramatcher-1.3.0.dist-info/top_level.txt
karton_yaramatcher-1.3.0.dist-info/RECORD
