Metadata-Version: 2.1
Name: karton-yaramatcher
Version: 1.3.0
Summary: File and analysis artifacts yara matcher for Karton framework
Home-page: https://github.com/CERT-Polska/karton-yaramatcher/
License: UNKNOWN
Platform: UNKNOWN
Classifier: Programming Language :: Python
Classifier: Operating System :: OS Independent
License-File: LICENSE
Requires-Dist: karton-core (<6.0.0,>=5.0.0)
Requires-Dist: yara-python (>=4.0.2)
